{
    "skills": [
      {
        "id": "1",
        "src": "./img/product-chain-1.png",
        "title": "Front-End",
        "description": "Lorem ipsum dolor sit amet, consectetur adipiscing elit. Suspenmdisse varius eim in eros elementum tristique "
      },
      {
        "id": "2",
        "src": "./img/tag-1.png",
        "title": "Back-End",
        "description": "Lorem ipsum dolor sit amet, consectetur adipiscing elit. Suspenmdisse varius eim in eros elementum tristique"
      },
      {
        "id": "3",
        "src": "./img/feather-pen-2.png",
        "title": "Web-Development",
        "description": "Lorem ipsum dolor sit amet, consectetur adipiscing elit. Suspenmdisse varius eim in eros elementum tristique"
      },
      {
        "id": "4",
        "src": "./img/feather-pen-1.png",
        "title": "IT",
        "description": "Lorem ipsum dolor sit amet, consectetur adipiscing elit. Suspenmdisse varius eim in eros elementum tristique"
      }
    ],
    "portfolio": [
      {
        "id": "1",
        "src": "./img/Sim.png",
        "title": "Covid sim",
        "description": "Lorem ipsum dolor sit amet, consectetur adipiscing elit. Suspenmdisse varius eim in eros elementum tristique",
        "link": "View In Github"
      },
      {
        "id": "2",
        "src": "./img/Sim.png",
        "title": "App Dashboard",
        "description": "Lorem ipsum dolor sit amet, consectetur adipiscing elit. Suspenmdisse varius eim in eros elementum tristique",
        "link": "View In Github"
      },
      {
        "id": "3",
        "src": "./img/Sim.png",
        "title": "Easy Rentn",
        "description": "Lorem ipsum dolor sit amet, consectetur adipiscing elit. Suspenmdisse varius eim in eros elementum tristique",
        "link": "View In Github"
      }
    ]

  }